afitop100/__init__.py
afitop100/__main__.py
afitop100/afi.py
afitop100/app.py
afitop100/film.py
afitop100/common/__init__.py
afitop100/common/wikipedia.py
tests/__init__.py
tests/test_afitop100.py
afitop100-0.1.0.dist-info/METADATA
afitop100-0.1.0.dist-info/WHEEL
afitop100-0.1.0.dist-info/entry_points.txt
afitop100-0.1.0.dist-info/top_level.txt
afitop100-0.1.0.dist-info/RECORD
