Metadata-Version: 2.1
Name: afitop100
Version: 0.1.0
Summary: UNKNOWN
Home-page: UNKNOWN
Author: UNKNOWN
Author-email: UNKNOWN
License: Creative Commons Attribution-Noncommercial-Share Alike license
Platform: UNKNOWN
Requires-Dist: beautifulsoup4
Requires-Dist: requests
Requires-Dist: flask
